pers_assist/address_book_classes.py
pers_assist/addressbook.py
pers_assist/main_menu.py
pers_assist/new_ABC.py
pers_assist/normalize.py
pers_assist/notes.py
pers_assist/sort.py
Personal_assistant_project-0.1.0.dist-info/METADATA
Personal_assistant_project-0.1.0.dist-info/WHEEL
Personal_assistant_project-0.1.0.dist-info/top_level.txt
Personal_assistant_project-0.1.0.dist-info/RECORD
