Metadata-Version: 2.1
Name: Personal-assistant-project
Version: 0.1.0
Summary: GoIT group project as personal assistant
Home-page: UNKNOWN
Author-email: moivvas@gmail.com
License: UNKNOWN
Platform: UNKNOWN
